securitylib/__init__.py
securitylib/advanced_crypto.py
securitylib/crypto.py
securitylib/dictionary.txt
securitylib/passwords.py
securitylib/random.py
securitylib/random_utils.py
securitylib/utils.py
securitylib/throttling/__init__.py
securitylib/throttling/client.py
securitylib/throttling/common.py
securitylib/throttling/server.py
securitylib-1.0.9.dist-info/LICENSE
securitylib-1.0.9.dist-info/METADATA
securitylib-1.0.9.dist-info/WHEEL
securitylib-1.0.9.dist-info/top_level.txt
securitylib-1.0.9.dist-info/RECORD
