Metadata-Version: 2.1
Name: securitylib
Version: 1.0.9
Summary: SAPO Security Lib - Python
Home-page: http://oss.sapo.pt/securitylib-python/
Author: Jose Nuno Pires
Author-email: José Nuno Pires <jose-n-pires@telecom.pt>
License: MIT License
Project-URL: Homepage, https://github.com/sapo/securitylib-python
Project-URL: Issues, https://github.com/sapo/securitylib-python/issues
Keywords: security,crypto,securitylib
Classifier: Programming Language :: Python :: 3
Classifier: Operating System :: OS Independent
Requires-Python: >=3.4
License-File: LICENSE
